medusa_protocol/__init__.py
medusa_protocol/exceptions.py
medusa_protocol/binary/Abstract.py
medusa_protocol/binary/BinaryRequest.py
medusa_protocol/binary/BinaryResponse.py
medusa_protocol/binary/__init__.py
medusa_protocol-0.0.2.dist-info/AUTHORS.rst
medusa_protocol-0.0.2.dist-info/METADATA
medusa_protocol-0.0.2.dist-info/WHEEL
medusa_protocol-0.0.2.dist-info/top_level.txt
medusa_protocol-0.0.2.dist-info/RECORD
