Metadata-Version: 2.1
Name: medusa-protocol
Version: 0.0.2
Summary: Library with the binary and not protocol
Home-page: UNKNOWN
Author: Andrea Mucci
Author-email: andrea@breda.build
License: UNKNOWN
Keywords: medusa_protocol
Platform: UNKNOWN
Classifier: Development Status :: 2 - Pre-Alpha
Classifier: Intended Audience :: Developers
Classifier: Natural Language :: English
Classifier: Programming Language :: Python :: 3
Classifier: Programming Language :: Python :: 3.5
Classifier: Programming Language :: Python :: 3.6
Classifier: Programming Language :: Python :: 3.7
Classifier: Programming Language :: Python :: 3.8
Requires-Python: >=3.5
Requires-Dist: msgpack
